MANIFEST.in
README.md
requirements.txt
setup.cfg
setup.py
flask_api_spec/__base__.py
flask_api_spec/__init__.py
flask_api_spec/component.py
flask_api_spec/exceptions.py
flask_api_spec/generate.py
flask_api_spec/intercept.py
flask_api_spec/value.py
flask_api_spec.egg-info/PKG-INFO
flask_api_spec.egg-info/SOURCES.txt
flask_api_spec.egg-info/dependency_links.txt
flask_api_spec.egg-info/requires.txt
flask_api_spec.egg-info/top_level.txt
flask_api_spec/static/swagger-ui-bundle.js
flask_api_spec/static/swagger-ui-standalone-preset.js
flask_api_spec/static/swagger-ui.css
flask_api_spec/templates/swagger.html