Metadata-Version: 1.1
Name: flask-api-spec
Version: 0.1.9
Summary: flask api toolset
Home-page: http://github.com/laberin/flask-api-spec/
Author: laberin
Author-email: eseom@msn.com
License: MIT
Platform: any
Classifier: Environment :: Web Environment
Classifier: Programming Language :: Python :: 2
Classifier: Programming Language :: Python :: 3
